Forage/__init__.py
Forage/erosion_data/__init__.py
baysalt/Select_zip.py
baysalt/Single_Forecast_js.py
baysalt/Single_Forecast_txt.py
baysalt/Singlepoint_Cangnan_tj.py
baysalt/Singlepoint_Cangnan_tj_2.py
baysalt/Singlepoint_Cangnan_tj_old.py
baysalt/__init__.py
baysalt/actual_harbor.py
baysalt/erosion_coastline.py
baysalt/pic_draw.py
baysalt/strDateTime.py
baysalt/Configures/__init__.py
baysalt/Examples/Example_conda_pack.py
baysalt/Examples/Example_copernicusmarine.py
baysalt/Examples/Example_pyforest.py
baysalt/Examples/Forecast_point_g2s.py
baysalt/Examples/__init__.py
baysalt/Examples/example_wheel_s2g.py
baysalt/Interp/Interp_g2s.py
baysalt/Interp/Interp_gfs_wind.py
baysalt/Interp/Interp_s2g.py
baysalt/Interp/Interp_s2s.py
baysalt/Interp/__init__.py
baysalt-0.1.0.8.dist-info/METADATA
baysalt-0.1.0.8.dist-info/WHEEL
baysalt-0.1.0.8.dist-info/top_level.txt
baysalt-0.1.0.8.dist-info/RECORD
