Metadata-Version: 2.1
Name: baysalt
Version: 0.1.0.8
Summary: Some simple tools for baysalt
Author: Christmas, Dovelet, Qidi Ma
Author-email: 273519355@qq.com
Classifier: Programming Language :: Python :: 3
Classifier: License :: OSI Approved :: MIT License
Classifier: Operating System :: OS Independent
Requires-Python: >=3.6
Requires-Dist: numpy
Requires-Dist: netCDF4
Requires-Dist: scipy
Requires-Dist: baysalt-christmas
